webnest/__init__.py
webnest/admin.py
webnest/handling.py
webnest/path.py
webnest/requestHandler.py
webnest/shortcuts.py
webnest/state_colors.py
webnest/tags.py
webnest/urls.py
webnest/db/__init__.py
webnest/db/databaseHandler.py
webnest/db/treks.py
webnest/example_project/Mydb.sqlite3
webnest/example_project/__init__.py
webnest/example_project/cli.py
webnest/example_project/handle.py
webnest/example_project/models.py
webnest/example_project/routes.py
webnest/example_project/settings.py
webnest/example_project/static/main.css
webnest/example_project/templates/index.html
webnest-0.1.1.dist-info/licenses/LICENSE.txt
webnest-0.1.1.dist-info/METADATA
webnest-0.1.1.dist-info/WHEEL
webnest-0.1.1.dist-info/entry_points.txt
webnest-0.1.1.dist-info/top_level.txt
webnest-0.1.1.dist-info/RECORD
