Metadata-Version: 2.4
Name: webnest
Version: 0.1.1
Summary: webnest (yahia web app package or framework) is a simple framework to create web application
Home-page: https://github.com/Black4315/webnest
Author: Yahia Badr
Author-email: yahialord4315@gmail.com
Classifier: Programming Language :: Python :: 3
Classifier: License :: OSI Approved :: MIT License
Classifier: Operating System :: OS Independent
Classifier: Environment :: Web Environment
Requires-Python: >=3.12.3
License-File: LICENSE.txt
Requires-Dist: Jinja2==3.1.4
Requires-Dist: colorama==0.4.6
Requires-Dist: black==24.8.0
Dynamic: author
Dynamic: author-email
Dynamic: classifier
Dynamic: description
Dynamic: description-content-type
Dynamic: home-page
Dynamic: license-file
Dynamic: requires-dist
Dynamic: requires-python
Dynamic: summary
